{
  "ip_address": "192.168.230.217",
  "export_date": "2025-04-12T19:54:48",
  "host_info": {
    "ip_address": "10.224.50.85",
    "mac_address": "92:83:ef:f6:91:4f",
    "mac_vendor": "Haynes-York",
    "dhcp_hostname": "canon_pixma",
    "os_fingerprint": "Canon_PIXMA",
    "lease_hostname": "canon_pixma"
  },
  "dns_queries": [
    "canon.com"
  ],
  "flows": [
    {
      "destination": "131.187.90.61",
      "port": 443,
      "protocol": 6
    },
    {
      "destination": "129.108.226.51",
      "port": 5000,
      "protocol": 17
    },
    {
      "destination": "162.183.199.69",
      "port": 443,
      "protocol": 17
    },
    {
      "destination": "222.82.67.22",
      "port": 53,
      "protocol": 6
    },
    {
      "destination": "203.77.243.176",
      "port": 6667,
      "protocol": 6
    },
    {
      "destination": "37.144.245.17",
      "port": 8883,
      "protocol": 6
    }
  ],
  "label": "Printer"
}