{
  "ip_address": "192.168.184.237",
  "export_date": "2025-01-08T06:51:29",
  "host_info": {
    "ip_address": "192.168.11.15",
    "mac_address": "fd:ba:91:4d:b4:d7",
    "mac_vendor": "Maldonado-Miles",
    "dhcp_hostname": "galaxy_tab",
    "os_fingerprint": "Galaxy_Tab",
    "lease_hostname": "galaxy_tab"
  },
  "dns_queries": [
    "samsung.com",
    "amazon.com",
    "apple.com"
  ],
  "flows": [
    {
      "destination": "147.35.22.41",
      "port": 53,
      "protocol": 17
    },
    {
      "destination": "17.19.223.124",
      "port": 80,
      "protocol": 17
    },
    {
      "destination": "46.26.170.233",
      "port": 53,
      "protocol": 17
    },
    {
      "destination": "134.241.237.19",
      "port": 53,
      "protocol": 6
    }
  ],
  "label": "Tablet"
}