{
  "ip_address": "192.168.193.36",
  "export_date": "2025-04-06T09:44:49",
  "host_info": {
    "ip_address": "10.140.5.205",
    "mac_address": "a6:0b:c5:54:bd:91",
    "mac_vendor": "Lopez LLC",
    "dhcp_hostname": "homepod",
    "os_fingerprint": "HomePod",
    "lease_hostname": "homepod"
  },
  "dns_queries": [
    "amazon.com",
    "spotify.com"
  ],
  "flows": [
    {
      "destination": "136.129.35.191",
      "port": 8883,
      "protocol": 17
    },
    {
      "destination": "174.82.54.160",
      "port": 5000,
      "protocol": 17
    },
    {
      "destination": "197.111.72.218",
      "port": 53,
      "protocol": 6
    },
    {
      "destination": "22.187.78.22",
      "port": 6667,
      "protocol": 6
    },
    {
      "destination": "175.17.47.167",
      "port": 5000,
      "protocol": 17
    },
    {
      "destination": "192.98.47.197",
      "port": 443,
      "protocol": 6
    }
  ],
  "label": "Smart Speaker"
}